pphysics/__init__.py
pphysics/force.py
pphysics-1.1.1.dist-info/LICENSE
pphysics-1.1.1.dist-info/METADATA
pphysics-1.1.1.dist-info/WHEEL
pphysics-1.1.1.dist-info/top_level.txt
pphysics-1.1.1.dist-info/RECORD
