Metadata-Version: 2.1
Name: pphysics
Version: 1.1.1
Summary: Package pphysics to use physics in pygame.
Home-page: https://nhatnguyenjhl.github.io
Author: James H. Lasker
Author-email: jameshlasker@gmail.com
Maintainer: James H. Lasker
Maintainer-email: jameshlasker@gmail.com
License: MIT License
Keywords: physics,pyphysics,pyame,jameshlasker,standard,federation
Classifier: License :: OSI Approved :: MIT License
Classifier: Topic :: Software Development :: Libraries :: Python Modules
Classifier: Operating System :: OS Independent
Classifier: Programming Language :: Python :: 3 :: Only
Classifier: Programming Language :: Python :: 3.8
Classifier: Programming Language :: Python :: 3.9
Classifier: Programming Language :: Python :: 3.10
Requires-Python: >=3.8
License-File: LICENSE
Requires-Dist: pygame (>=3.8)
